[
  {
    "yomikata": "パン",
    "word": "",
    "mean": "bread; pastries (e.g. croissants); pastry-based products / pan; frying pan / panning (in a film)"
  },
  {
    "yomikata": "ぎんこう",
    "word": "銀行",
    "mean": "bank"
  },
  {
    "yomikata": "どれ",
    "word": "何れ",
    "mean": "which (of three or more) / whichever; any / well; now; let me see"
  },
  {
    "yomikata": "シャワー",
    "word": "",
    "mean": "shower"
  },
  {
    "yomikata": "どう",
    "word": "如何",
    "mean": "how; in what way; how about"
  },
  {
    "yomikata": "おじいさん",
    "word": "お祖父さん",
    "mean": "grandfather / male senior-citizen"
  },
  {
    "yomikata": "からい",
    "word": "辛い",
    "mean": "spicy; hot / salty / harsh (criticism); severe (punishment); strict / painful; bitter; difficult; tough"
  },
  {
    "yomikata": "カレー",
    "word": "咖哩",
    "mean": "curry / rice and curry"
  },
  {
    "yomikata": "スカート",
    "word": "",
    "mean": "skirt"
  },
  {
    "yomikata": "なぜ",
    "word": "何故",
    "mean": "why; how"
  },
  {
    "yomikata": "つとめる",
    "word": "勤める",
    "mean": "to work (for); to be employed (at); to serve (in) / to serve (as); to act (as); to fill (the position of); to play the role (of) / to conduct a religious service"
  },
  {
    "yomikata": "たんじょうび",
    "word": "誕生日",
    "mean": "birthday"
  },
  {
    "yomikata": "ひだり",
    "word": "左",
    "mean": "left; left hand side"
  },
  {
    "yomikata": "みがく",
    "word": "磨く",
    "mean": "to polish; to shine; to brush (e.g. teeth); to grind (e.g. lens) / to refine (e.g. a skill); to improve; to cultivate"
  },
  {
    "yomikata": "つよい",
    "word": "強い",
    "mean": "strong; potent; competent; domineering; tough / strong; brawny; powerful; healthy; rugged / good (at); skilled; knowledgeable / being able to handle; know how to deal (with); durable (against); resistant (to); resilient / firm; rigid; solid / intense; strong; fierce; high / dependable; trustworthy"
  },
  {
    "yomikata": "だいすき",
    "word": "大好き",
    "mean": "loveable; very likeable; like very much"
  },
  {
    "yomikata": "せん",
    "word": "千",
    "mean": "1,000; thousand"
  },
  {
    "yomikata": "カップ",
    "word": "",
    "mean": "cup (drinking vessel, measure, brassiere, prize, etc.) / instant noodles purchased in cup; cup noodles"
  },
  {
    "yomikata": "あね",
    "word": "姉",
    "mean": "older sister; elder sister"
  },
  {
    "yomikata": "じかん",
    "word": "時間",
    "mean": "time / hour"
  },
  {
    "yomikata": "せ",
    "word": "背",
    "mean": "back; spine / reverse; rear side / height; stature / ridge (of a mountain)"
  },
  {
    "yomikata": "くに",
    "word": "国",
    "mean": "country; state / region / national government; central government / home (i.e. hometown, home country) / province (of Japan) / land; earth"
  },
  {
    "yomikata": "いくつ",
    "word": "幾つ",
    "mean": "how many? / how old?"
  },
  {
    "yomikata": "しんぶん",
    "word": "新聞",
    "mean": "newspaper"
  },
  {
    "yomikata": "ところ",
    "word": "所",
    "mean": "place; spot; scene; site / address / district; area; locality / one's house / point; aspect; side; facet / passage (in text); part / space; room / thing; matter / whereupon; as a result / about to; on the verge of / was just doing; was in the process of doing; have just done; just finished doing"
  },
  {
    "yomikata": "たぶん",
    "word": "多分",
    "mean": "perhaps; probably / generous; many; much; great"
  },
  {
    "yomikata": "ナイフ",
    "word": "",
    "mean": "knife"
  },
  {
    "yomikata": "きらい",
    "word": "嫌い",
    "mean": "disliked; hated; disagreeable / tendency; smack (of); touch (of) / distinction; discrimination"
  },
  {
    "yomikata": "いつも",
    "word": "何時も",
    "mean": "always; usually; every time / never"
  },
  {
    "yomikata": "いくら",
    "word": "幾ら",
    "mean": "how much?; how many? / even; even if"
  },
  {
    "yomikata": "きく",
    "word": "聞く",
    "mean": "to hear / to listen (e.g. to music) / to ask; to enquire; to query / to learn of; to hear about / to follow (advice); to comply with / to smell (esp. incense); to sample fragrance"
  },
  {
    "yomikata": "つく",
    "word": "着く",
    "mean": "to arrive at; to reach / to sit on; to sit at (e.g. the table)"
  },
  {
    "yomikata": "みょうにち",
    "word": "明日",
    "mean": "tomorrow / near future"
  },
  {
    "yomikata": "ろうか",
    "word": "廊下",
    "mean": "corridor; hallway; passageway"
  },
  {
    "yomikata": "さす",
    "word": "差す",
    "mean": "to shine / to be visible / to be tinged with / to rise (of water levels); to flow in / to be felt (i.e. as an emotion); to come over one / to hold up (an umbrella, etc.); to put up; to raise / to extend one's arm straight ahead (in dance) / to insert; to put in / to wear (a sword) in one's belt; to wear at one's side; to carry under one's arm / to insert one's arm under an opponent's arm / to pole (a boat) / to pour; to add (liquid); to serve (drinks) / to put on (lipstick, etc.); to apply; to colour; to dye / to light (a fire); to burn / to shut; to close; to lock; to fasten / to stop in the midst of; to leave undone"
  },
  {
    "yomikata": "みる",
    "word": "見る",
    "mean": "to see; to look; to watch; to view; to observe / to look over; to look on; to assess; to examine; to judge / to look after; to keep an eye on; to take care of / to view (e.g. flowers, movie) / to try; to try out; to test / to see that...; to find that..."
  },
  {
    "yomikata": "くろい",
    "word": "黒い",
    "mean": "black / dark; blackish; sun-tanned (skin) / suspicious; criminal; illicit / darkened and dirty; sooty; covered in dirt / evil; wicked; black-hearted / inauspicious; ill-boding; unlucky"
  },
  {
    "yomikata": "きる",
    "word": "切る",
    "mean": "to cut; to cut through; to perform (surgery) / to sever (connections, ties) / to turn off (e.g. the light) / to terminate (e.g. a conversation); to hang up (the phone); to disconnect / to punch (a ticket); to tear off (a stub) / to open (something sealed) / to start / to set (a limit); to do (something) in less or within a certain time; to issue (stamps, vouchers, etc.) / to reduce; to decrease; to discount / to shake off (water, etc.); to let drip-dry; to let drain / to cross; to traverse / to criticize sharply / to act decisively; to do (something noticeable); to go first; to make (certain facial expressions, in kabuki) / to turn (vehicle, steering wheel, etc.) / to curl (a ball); to bend; to cut / to shuffle (cards) / to discard a tile / to dismiss; to sack; to let go; to expulse; to excommunicate / to dig (a groove); to cut (a stencil, on a mimeograph) / to trump / to cut (the connection between two groups) (in go) / to start a fire (with wood-wood friction or by striking a metal against stone) / to draw (a shape) in the air (with a sword, etc.) / to finish; to complete"
  },
  {
    "yomikata": "がいこく",
    "word": "外国",
    "mean": "foreign country"
  },
  {
    "yomikata": "むら",
    "word": "村",
    "mean": "village"
  },
  {
    "yomikata": "ハンカチ",
    "word": "",
    "mean": "handkerchief"
  },
  {
    "yomikata": "くつした",
    "word": "靴下",
    "mean": "socks; sock; stockings; stocking"
  },
  {
    "yomikata": "くすり",
    "word": "薬",
    "mean": "medicine; pharmaceuticals; (legal) drugs; pill; ointment; salve / efficacious chemical (gunpowder, pesticide, etc.) / (pottery) glaze / small bribe"
  },
  {
    "yomikata": "テーブル",
    "word": "",
    "mean": "table"
  },
  {
    "yomikata": "かてい",
    "word": "家庭",
    "mean": "home; family; household"
  },
  {
    "yomikata": "たくさん",
    "word": "沢山",
    "mean": "a lot; lots; plenty; many; a large number; much; a great deal; a good deal / enough; sufficient / enough; too many; too much"
  },
  {
    "yomikata": "ちゃわん",
    "word": "茶碗",
    "mean": "rice bowl; tea cup; teacup"
  },
  {
    "yomikata": "ページ",
    "word": "頁",
    "mean": "page"
  },
  {
    "yomikata": "ホテル",
    "word": "",
    "mean": "hotel"
  },
  {
    "yomikata": "しまる",
    "word": "閉まる",
    "mean": "to be shut; to close; to be closed / to be firm (of a body, face, etc.); to be well-knit / to be locked / to tighten; to be tightened / to become sober; to become tense"
  },
  {
    "yomikata": "すぐに",
    "word": "直ぐに",
    "mean": "immediately; right away; at once; instantly"
  },
  {
    "yomikata": "しゅくだい",
    "word": "宿題",
    "mean": "homework; assignment / pending issue; unresolved problem; open question"
  },
  {
    "yomikata": "たて",
    "word": "縦",
    "mean": "the vertical; height / front-to-back; length / north-to-south / vertical (relationship); hierarchy / (weaving) warp"
  },
  {
    "yomikata": "あらう",
    "word": "洗う",
    "mean": "to wash; to cleanse; to rinse / to inquire into; to investigate / to purify (one's heart) / to lave (e.g. shore); to wash over (e.g. deck); to sweep"
  },
  {
    "yomikata": "まち",
    "word": "町",
    "mean": "town; block; neighbourhood; neighborhood / street; road / 109.09 m / 0.99 hectares / downtown; main street"
  },
  {
    "yomikata": "する",
    "word": "為る",
    "mean": "to do; to carry out; to perform / to cause to become; to make (into); to turn (into) / to serve as; to act as; to work as / to wear (clothes, a facial expression, etc.) / to judge as being; to view as being; to think of as; to treat as; to use as / to decide on; to choose / to be sensed (of a smell, noise, etc.) / to be (in a state, condition, etc.) / to be worth; to cost / to pass (of time); to elapse / to place, or raise, person A to a post or status B / to transform A to B; to make A into B; to exchange A for B / to make use of A for B; to view A as B; to handle A as if it were B / to feel A about B / verbalizing suffix (applies to nouns noted in this dictionary with the part of speech \"vs) / creates a humble verb (after a noun prefixed with \"o\" or \"go\") / to be just about to; to be just starting to; to try to; to attempt to\""
  },
  {
    "yomikata": "ひがし",
    "word": "東",
    "mean": "east"
  },
  {
    "yomikata": "とり",
    "word": "鳥",
    "mean": "bird / bird meat (esp. chicken meat); fowl; poultry"
  },
  {
    "yomikata": "あし",
    "word": "足",
    "mean": "foot / leg / gait / pace / bottom structural component (i.e. radical) of a kanji / means of transportation / money; coin"
  },
  {
    "yomikata": "おとな",
    "word": "大人",
    "mean": "adult"
  },
  {
    "yomikata": "つめたい",
    "word": "冷たい",
    "mean": "cold (to the touch); chilly; icy; freezing / coldhearted; unfeeling; indifferent; unfriendly"
  },
  {
    "yomikata": "でぐち",
    "word": "出口",
    "mean": "exit; gateway; way out; outlet; leak; vent"
  },
  {
    "yomikata": "やすむ",
    "word": "休む",
    "mean": "to be absent; to take a day off / to rest; to have a break / to go to bed; to (lie down to) sleep; to turn in; to retire / to stop doing some ongoing activity for a time; to suspend business"
  },
  {
    "yomikata": "ゆうめい",
    "word": "有名",
    "mean": "famous / fame"
  },
  {
    "yomikata": "ポケット",
    "word": "",
    "mean": "pocket"
  },
  {
    "yomikata": "おおきい",
    "word": "大きい",
    "mean": "big; large; great / loud / extensive; spacious / important; decisive; valuable / older; grown up"
  },
  {
    "yomikata": "こたえる",
    "word": "答える",
    "mean": "to answer; to reply"
  },
  {
    "yomikata": "と",
    "word": "戸",
    "mean": "door (esp. Japanese-style) / shutter; window shutter / entrance (to a home) / narrows"
  },
  {
    "yomikata": "め",
    "word": "目",
    "mean": "eye; eyeball / eyesight; sight; vision / look; stare; glance / an experience / viewpoint / stitch; texture; weave / ordinal number suffix / somewhat; -ish"
  },
  {
    "yomikata": "しぬ",
    "word": "死ぬ",
    "mean": "to die; to pass away / to lose spirit; to lose vigor; to look dead / to cease; to stop"
  },
  {
    "yomikata": "プール",
    "word": "",
    "mean": "(swimming) pool / pool (billiards) / pool (together)"
  },
  {
    "yomikata": "ならべる",
    "word": "並べる",
    "mean": "to line up; to set up; to arrange in a line / to enumerate; to itemize / to be equal (to); to compare well (with); to be as good (as)"
  },
  {
    "yomikata": "きいろい",
    "word": "黄色い",
    "mean": "yellow / high-pitched (voice); shrill"
  },
  {
    "yomikata": "きる",
    "word": "着る",
    "mean": "to wear (in modern Japanese, from the shoulders down); to put on / to bear (guilt, etc.)"
  },
  {
    "yomikata": "うわぎ",
    "word": "上着",
    "mean": "coat; tunic; jacket; outer garment"
  },
  {
    "yomikata": "ざっし",
    "word": "雑誌",
    "mean": "journal; magazine; periodical"
  },
  {
    "yomikata": "いれる",
    "word": "入れる",
    "mean": "to put in; to let in; to take in; to bring in; to insert; to set (a jewel, etc.); to ink in (e.g. a tattoo) / to admit; to accept; to employ; to hire / to accept; to comply; to grant; to adopt (a policy, etc.); to take (advice, etc.); to listen to; to pay attention to / to include / to pay (one's rent, etc.) / to cast (a vote) / to make (tea, coffee, etc.) / to turn on (a switch, etc.) / to send (a fax); to call"
  },
  {
    "yomikata": "ドア",
    "word": "",
    "mean": "door (Western-style)"
  },
  {
    "yomikata": "せびろ",
    "word": "背広",
    "mean": "business suit"
  },
  {
    "yomikata": "こちら",
    "word": "此方",
    "mean": "this way (direction close to the speaker or towards the speaker); this direction / here (place close to the speaker or where the speaker is) / this one (something physically close to the speaker) / I; me; we; us / this person (someone physically close to the speaker and of equal or higher status)"
  },
  {
    "yomikata": "いちにち",
    "word": "一日",
    "mean": "one day / first day of the month"
  },
  {
    "yomikata": "ちがう",
    "word": "違う",
    "mean": "to differ (from); to vary / to not be in the usual condition / to not match the correct (answer, etc.) / to be different from promised / isn't it?; wasn't it?"
  },
  {
    "yomikata": "こんしゅう",
    "word": "今週",
    "mean": "this week"
  },
  {
    "yomikata": "やっつ",
    "word": "八つ",
    "mean": "eight"
  },
  {
    "yomikata": "ください",
    "word": "下さい",
    "mean": "please give me / please do for me"
  },
  {
    "yomikata": "せっけん",
    "word": "石鹸",
    "mean": "soap"
  },
  {
    "yomikata": "だいがく",
    "word": "大学",
    "mean": "university; college / former central university of Kyoto (established under the ritsuryo system for the training of government administrators) / the Great Learning (one of the Four Books)"
  },
  {
    "yomikata": "いもうと",
    "word": "妹",
    "mean": "younger sister"
  },
  {
    "yomikata": "ぬるい",
    "word": "温い",
    "mean": "lukewarm; tepid / lenient / slow; stupid"
  },
  {
    "yomikata": "やおや",
    "word": "八百屋",
    "mean": "greengrocer"
  },
  {
    "yomikata": "はれ",
    "word": "晴れ",
    "mean": "clear weather; fine weather / formal; ceremonial; public / cleared of suspicion"
  },
  {
    "yomikata": "おぼえる",
    "word": "覚える",
    "mean": "to memorize; to memorise; to commit to memory; to learn by heart; to bear in mind; to remember / to learn; to pick up; to acquire / to feel / to think; to regard"
  },
  {
    "yomikata": "あく",
    "word": "開く",
    "mean": "to open (e.g. doors) / to open (e.g. business, etc.) / to be empty / to be vacant; to be available; to be free / to be open (e.g. neckline, etc.) / to have been opened (of one's eyes, mouth, etc.) / to come to an end / to open (one's eyes, mouth, etc.) / to have a hole; to form a gap; to have an interval (between events)"
  },
  {
    "yomikata": "テレビ",
    "word": "",
    "mean": "television; TV / TV program; TV programme; TV broadcast"
  },
  {
    "yomikata": "あのう",
    "word": "",
    "mean": "say; well; errr ..."
  },
  {
    "yomikata": "こんばん",
    "word": "今晩",
    "mean": "tonight; this evening"
  },
  {
    "yomikata": "よん",
    "word": "四",
    "mean": "four"
  },
  {
    "yomikata": "おわる",
    "word": "終わる",
    "mean": "to finish; to end; to close"
  },
  {
    "yomikata": "ある",
    "word": "在る",
    "mean": "to be; to exist; to live / to have / to be located / to be equipped with / to happen; to come about"
  },
  {
    "yomikata": "かみ",
    "word": "紙",
    "mean": "paper"
  },
  {
    "yomikata": "ほん",
    "word": "本",
    "mean": "book; volume; script / this; present / main; head / real; regular / counter for long cylindrical things; counter for films, TV shows, etc.; counter for goals, home runs, etc.; counter for telephone calls"
  },
  {
    "yomikata": "いぬ",
    "word": "犬",
    "mean": "dog (Canis (lupus) familiaris) / snoop (i.e. a detective, a spy, etc.) / loser; asshole / counterfeit; inferior; useless; wasteful"
  },
  {
    "yomikata": "こんにち",
    "word": "今日",
    "mean": "today; this day / these days; recently; nowadays"
  },
  {
    "yomikata": "かぜ",
    "word": "風",
    "mean": "wind; breeze; draught; draft / manner; behaviour; behavior / cold; influenza"
  },
  {
    "yomikata": "はち",
    "word": "八",
    "mean": "eight"
  },
  {
    "yomikata": "やさしい",
    "word": "易しい",
    "mean": "easy; plain; simple"
  },
  {
    "yomikata": "ようふく",
    "word": "洋服",
    "mean": "Western-style clothes (cf. traditional Japanese clothes)"
  },
  {
    "yomikata": "らいげつ",
    "word": "来月",
    "mean": "next month"
  },
  {
    "yomikata": "あき",
    "word": "秋",
    "mean": "autumn; fall"
  },
  {
    "yomikata": "きた",
    "word": "北",
    "mean": "north / the North; northern territories / North Korea / north wind"
  },
  {
    "yomikata": "ちゃいろ",
    "word": "茶色",
    "mean": "light brown; tawny"
  },
  {
    "yomikata": "コート",
    "word": "",
    "mean": "coat / court (i.e. tennis, basketball, etc.)"
  },
  {
    "yomikata": "はじまる",
    "word": "始まる",
    "mean": "to begin; to start; to commence / to happen (again); to begin (anew) / to date (from); to originate (in)"
  },
  {
    "yomikata": "はいざら",
    "word": "灰皿",
    "mean": "ashtray"
  },
  {
    "yomikata": "それから",
    "word": "其れから",
    "mean": "and then; after that"
  },
  {
    "yomikata": "せいと",
    "word": "生徒",
    "mean": "pupil; student; schoolchild"
  },
  {
    "yomikata": "ばん",
    "word": "晩",
    "mean": "evening / counter for nights"
  },
  {
    "yomikata": "あまり",
    "word": "余り",
    "mean": "remainder; remnant; rest; balance; surplus; remains (of a meal); leftovers / not very; not much / too much; excessively; overly / extreme; great; severe; tremendous; terrible / more than; over"
  },
  {
    "yomikata": "さらいねん",
    "word": "再来年",
    "mean": "year after next"
  },
  {
    "yomikata": "おんな",
    "word": "女",
    "mean": "female; woman; female sex / female lover; girlfriend; mistress; (someone's) woman"
  }
]