[
  {
    "yomikata": "ヨーロッパ",
    "word": "欧羅巴",
    "mean": "Europe"
  },
  {
    "yomikata": "しまった",
    "word": "仕舞った",
    "mean": "damn it!; oh no!"
  },
  {
    "yomikata": "ボール",
    "word": "",
    "mean": "ball"
  },
  {
    "yomikata": "よなか",
    "word": "夜中",
    "mean": "middle of the night"
  },
  {
    "yomikata": "ほうこう",
    "word": "方向",
    "mean": "direction"
  },
  {
    "yomikata": "このむ",
    "word": "好む",
    "mean": "to like; to prefer"
  },
  {
    "yomikata": "ひも",
    "word": "紐",
    "mean": "string; cord"
  },
  {
    "yomikata": "せいき",
    "word": "世紀",
    "mean": "century"
  },
  {
    "yomikata": "さけ",
    "word": "酒",
    "mean": "alcohol; sake"
  },
  {
    "yomikata": "ひづけ",
    "word": "日付",
    "mean": "date"
  },
  {
    "yomikata": "えん",
    "word": "縁",
    "mean": "fate; connection"
  },
  {
    "yomikata": "よぼう",
    "word": "予防",
    "mean": "prevention"
  },
  {
    "yomikata": "デモ",
    "word": "",
    "mean": "demonstration; protest"
  },
  {
    "yomikata": "とびだす",
    "word": "飛び出す",
    "mean": "to jump out; to rush out"
  },
  {
    "yomikata": "はかせ",
    "word": "博士",
    "mean": "doctor; PhD"
  },
  {
    "yomikata": "たび",
    "word": "旅",
    "mean": "trip; journey"
  },
  {
    "yomikata": "えんぎ",
    "word": "演技",
    "mean": "acting; performance"
  },
  {
    "yomikata": "はくぶつかん",
    "word": "博物館",
    "mean": "museum"
  },
  {
    "yomikata": "くりかえす",
    "word": "繰り返す",
    "mean": "to repeat"
  },
  {
    "yomikata": "とうひょう",
    "word": "投票",
    "mean": "voting"
  },
  {
    "yomikata": "けっか",
    "word": "結果",
    "mean": "result; outcome"
  },
  {
    "yomikata": "ほう",
    "word": "法",
    "mean": "law; method"
  },
  {
    "yomikata": "た",
    "word": "他",
    "mean": "other; others"
  },
  {
    "yomikata": "ち",
    "word": "地",
    "mean": "ground; land"
  },
  {
    "yomikata": "あたえる",
    "word": "与える",
    "mean": "to give; to provide"
  },
  {
    "yomikata": "たよる",
    "word": "頼る",
    "mean": "to rely on; to depend on"
  },
  {
    "yomikata": "つり",
    "word": "釣り",
    "mean": "fishing"
  },
  {
    "yomikata": "ちゅうしょく",
    "word": "昼食",
    "mean": "lunch"
  },
  {
    "yomikata": "ひこう",
    "word": "飛行",
    "mean": "flight; flying"
  },
  {
    "yomikata": "せいしき",
    "word": "正式",
    "mean": "official; formal"
  },
  {
    "yomikata": "たんじゅん",
    "word": "単純",
    "mean": "simple"
  },
  {
    "yomikata": "せい",
    "word": "正",
    "mean": "correct; true"
  },
  {
    "yomikata": "たく",
    "word": "宅",
    "mean": "house; home"
  },
  {
    "yomikata": "くべつ",
    "word": "区別",
    "mean": "distinction; differentiation"
  },
  {
    "yomikata": "こえる",
    "word": "越える",
    "mean": "to cross; to go beyond"
  },
  {
    "yomikata": "ものおと",
    "word": "物音",
    "mean": "sounds; noise"
  },
  {
    "yomikata": "こんざつ",
    "word": "混雑",
    "mean": "congestion; crowding"
  },
  {
    "yomikata": "こし",
    "word": "腰",
    "mean": "waist; lower back"
  },
  {
    "yomikata": "かわいそう",
    "word": "可哀相",
    "mean": "pitiful; poor"
  },
  {
    "yomikata": "たいくつ",
    "word": "退屈",
    "mean": "boredom"
  },
  {
    "yomikata": "あいず",
    "word": "合図",
    "mean": "sign; signal"
  },
  {
    "yomikata": "どうりょう",
    "word": "同僚",
    "mean": "coworker; colleague"
  },
  {
    "yomikata": "かご",
    "word": "籠",
    "mean": "basket"
  },
  {
    "yomikata": "ほほえむ",
    "word": "微笑む",
    "mean": "to smile"
  },
  {
    "yomikata": "よみ",
    "word": "読み",
    "mean": "reading"
  },
  {
    "yomikata": "いわゆる",
    "word": "所謂",
    "mean": "so-called"
  },
  {
    "yomikata": "げんざい",
    "word": "現在",
    "mean": "now; present"
  },
  {
    "yomikata": "てんねん",
    "word": "天然",
    "mean": "natural; nature"
  },
  {
    "yomikata": "うめ",
    "word": "梅",
    "mean": "plum; Japanese apricot"
  },
  {
    "yomikata": "いっそう",
    "word": "一層",
    "mean": "even more; all the more"
  },
  {
    "yomikata": "てき",
    "word": "敵",
    "mean": "enemy; opponent"
  },
  {
    "yomikata": "だいじん",
    "word": "大臣",
    "mean": "cabinet minister"
  },
  {
    "yomikata": "しじん",
    "word": "詩人",
    "mean": "poet"
  },
  {
    "yomikata": "ある",
    "word": "或",
    "mean": "a certain ~; some ~"
  },
  {
    "yomikata": "けんとう",
    "word": "検討",
    "mean": "consideration; examination"
  },
  {
    "yomikata": "かいぜん",
    "word": "改善",
    "mean": "improvement"
  },
  {
    "yomikata": "れい",
    "word": "例",
    "mean": "example; case"
  },
  {
    "yomikata": "じょうきょう",
    "word": "上京",
    "mean": "going to Tokyo"
  },
  {
    "yomikata": "たんなる",
    "word": "単なる",
    "mean": "mere; simple"
  },
  {
    "yomikata": "とおす",
    "word": "通す",
    "mean": "to let pass; to carry through"
  },
  {
    "yomikata": "さいてい",
    "word": "最低",
    "mean": "lowest; worst"
  },
  {
    "yomikata": "せいかく",
    "word": "性格",
    "mean": "character; personality"
  },
  {
    "yomikata": "いき",
    "word": "息",
    "mean": "breath"
  },
  {
    "yomikata": "カー",
    "word": "",
    "mean": "car"
  },
  {
    "yomikata": "せきにん",
    "word": "責任",
    "mean": "responsibility"
  },
  {
    "yomikata": "たがい",
    "word": "互い",
    "mean": "mutual; each other"
  },
  {
    "yomikata": "すがた",
    "word": "姿",
    "mean": "figure; appearance"
  },
  {
    "yomikata": "こうけん",
    "word": "貢献",
    "mean": "contribution"
  },
  {
    "yomikata": "せいふ",
    "word": "政府",
    "mean": "government"
  },
  {
    "yomikata": "げんじつ",
    "word": "現実",
    "mean": "reality"
  },
  {
    "yomikata": "じゅうみん",
    "word": "住民",
    "mean": "resident; inhabitant"
  },
  {
    "yomikata": "ば",
    "word": "場",
    "mean": "place; scene"
  },
  {
    "yomikata": "ひろがる",
    "word": "広がる",
    "mean": "to spread; to extend"
  },
  {
    "yomikata": "うまれ",
    "word": "生まれ",
    "mean": "birth; birthplace"
  },
  {
    "yomikata": "はじまり",
    "word": "始まり",
    "mean": "beginning; start"
  },
  {
    "yomikata": "ふし",
    "word": "節",
    "mean": "joint; tune"
  },
  {
    "yomikata": "げんしょう",
    "word": "現象",
    "mean": "phenomenon"
  },
  {
    "yomikata": "すばらしい",
    "word": "素晴らしい",
    "mean": "wonderful; splendid"
  },
  {
    "yomikata": "え",
    "word": "柄",
    "mean": "handle; grip"
  },
  {
    "yomikata": "トンネル",
    "word": "",
    "mean": "tunnel"
  },
  {
    "yomikata": "ゆうじん",
    "word": "友人",
    "mean": "friend"
  },
  {
    "yomikata": "しょうがくきん",
    "word": "奨学金",
    "mean": "scholarship"
  },
  {
    "yomikata": "ふと",
    "word": "不図",
    "mean": "suddenly; unexpectedly"
  },
  {
    "yomikata": "しんけい",
    "word": "神経",
    "mean": "nerve; nerves"
  },
  {
    "yomikata": "えいきょう",
    "word": "影響",
    "mean": "influence; effect"
  },
  {
    "yomikata": "ぜんぜん",
    "word": "全然",
    "mean": "not at all (with neg.); completely"
  },
  {
    "yomikata": "せいちょう",
    "word": "成長",
    "mean": "growth; development"
  },
  {
    "yomikata": "ばめん",
    "word": "場面",
    "mean": "scene; situation"
  },
  {
    "yomikata": "いんさつ",
    "word": "印刷",
    "mean": "printing"
  },
  {
    "yomikata": "くんれん",
    "word": "訓練",
    "mean": "training"
  },
  {
    "yomikata": "やね",
    "word": "屋根",
    "mean": "roof"
  },
  {
    "yomikata": "さっか",
    "word": "作家",
    "mean": "author; writer"
  },
  {
    "yomikata": "たいする",
    "word": "対する",
    "mean": "to face; to oppose"
  },
  {
    "yomikata": "げ",
    "word": "下",
    "mean": "lower; below"
  },
  {
    "yomikata": "ひょうじょう",
    "word": "表情",
    "mean": "facial expression"
  },
  {
    "yomikata": "はら",
    "word": "腹",
    "mean": "stomach; belly"
  },
  {
    "yomikata": "じょうとう",
    "word": "上等",
    "mean": "first-class; excellent"
  },
  {
    "yomikata": "のう",
    "word": "能",
    "mean": "ability; Noh theatre"
  },
  {
    "yomikata": "けんちく",
    "word": "建築",
    "mean": "architecture; construction"
  },
  {
    "yomikata": "けいき",
    "word": "景気",
    "mean": "economic conditions; business climate"
  },
  {
    "yomikata": "しょう",
    "word": "小",
    "mean": "small; elementary"
  },
  {
    "yomikata": "いりょう",
    "word": "医療",
    "mean": "medical care; medical treatment"
  },
  {
    "yomikata": "あらた",
    "word": "新た",
    "mean": "new"
  },
  {
    "yomikata": "どくとく",
    "word": "独特",
    "mean": "unique; distinctive"
  },
  {
    "yomikata": "にち",
    "word": "日",
    "mean": "day; Japan"
  },
  {
    "yomikata": "のこり",
    "word": "残り",
    "mean": "remaining; the rest"
  },
  {
    "yomikata": "さつ",
    "word": "札",
    "mean": "bill; paper money"
  },
  {
    "yomikata": "しばしば",
    "word": "屡々",
    "mean": "often; frequently"
  },
  {
    "yomikata": "さくもつ",
    "word": "作物",
    "mean": "crops; produce"
  },
  {
    "yomikata": "だれか",
    "word": "誰か",
    "mean": "someone"
  },
  {
    "yomikata": "ほね",
    "word": "骨",
    "mean": "bone"
  },
  {
    "yomikata": "さす",
    "word": "指す",
    "mean": "to point; to indicate"
  },
  {
    "yomikata": "どうか",
    "word": "銅貨",
    "mean": "copper coin"
  },
  {
    "yomikata": "おぼれる",
    "word": "溺れる",
    "mean": "to drown; to indulge in"
  },
  {
    "yomikata": "ひとしい",
    "word": "等しい",
    "mean": "equal; the same"
  },
  {
    "yomikata": "しょうじょう",
    "word": "症状",
    "mean": "symptoms"
  },
  {
    "yomikata": "やど",
    "word": "宿",
    "mean": "inn; lodging"
  },
  {
    "yomikata": "ど",
    "word": "度",
    "mean": "degree; time(s)"
  },
  {
    "yomikata": "げんご",
    "word": "言語",
    "mean": "language"
  },
  {
    "yomikata": "かがやく",
    "word": "輝く",
    "mean": "to shine; to glitter"
  }
]
